sphinxx/ret_calcs/__init__.py
sphinxx/ret_calcs/taxes.py
sphinxx_ret_calcs-0.0.2.dist-info/licenses/LICENSE.txt
sphinxx_ret_calcs-0.0.2.dist-info/METADATA
sphinxx_ret_calcs-0.0.2.dist-info/WHEEL
sphinxx_ret_calcs-0.0.2.dist-info/top_level.txt
sphinxx_ret_calcs-0.0.2.dist-info/RECORD
