Metadata-Version: 2.4
Name: sphinxx-ret_calcs
Version: 0.0.2
Summary: specific use-case retirement calculations: OAS, GIS, allowance, CPP and RRIF/annuity + taxes. Not intended for public use, though available under CC BY-NC 4.0 license (non-commercial use, attribution required, all rights reserved)
Author: Odysseus
Classifier: Programming Language :: Python :: 3
Classifier: License :: OSI Approved
Classifier: Operating System :: Microsoft :: Windows
License-File: LICENSE.txt
Requires-Dist: sphinxx
Dynamic: license-file
